golgi/__init__.py
golgi/app.py
golgi/annotation/__init__.py
golgi/annotation/auto_annotation.py
golgi/annotation/config.py
golgi/annotation/drawing.py
golgi/annotation/image_annotation.py
golgi/annotation/main.py
golgi/annotation/model.py
golgi/date_utils/__init__.py
golgi/date_utils/date_utils.py
golgi/inference/__init__.py
golgi/inference/config.py
golgi/inference/data_handler.py
golgi/inference/image_processing.py
golgi/inference/inference_pipeline.py
golgi/inference/main.py
golgi/inference/util.py
golgi/inference/weight_manager.py
golgi/plotting/__init__.py
golgi/plotting/updateable_plot.py
golgi/settings/__init__.py
golgi/settings/default_settings.json
golgi/settings/settings.py
golgi/temp/.gitkeep
golgi/training/__init__.py
golgi/training/configs.py
golgi/training/main.py
golgi/training/trainer.py
golgi/weights/.gitkeep
golgi_cell_cv-0.15.dist-info/LICENSE
golgi_cell_cv-0.15.dist-info/METADATA
golgi_cell_cv-0.15.dist-info/WHEEL
golgi_cell_cv-0.15.dist-info/entry_points.txt
golgi_cell_cv-0.15.dist-info/top_level.txt
golgi_cell_cv-0.15.dist-info/RECORD
